_pysseract.cpython-36m-i386-linux-gnu.so
pysseract/__init__.py
.libs_pysseract/libgomp-29d78f0c.so.1.0.0
.libs_pysseract/libtiff-31056aef.so.5.2.0
.libs_pysseract/libz-2a50ca1f.so.1.2.7
.libs_pysseract/libtesseract-f831b82a.so.4.0.1
.libs_pysseract/libjpeg-2be6cb98.so.62.1.0
.libs_pysseract/libjbig-2a826335.so.2.0
.libs_pysseract/libpng15-8d3d3d37.so.15.13.0
.libs_pysseract/liblept-08997937.so.5.0.3
pysseract-1.3.1.dist-info/top_level.txt
pysseract-1.3.1.dist-info/RECORD
pysseract-1.3.1.dist-info/METADATA
pysseract-1.3.1.dist-info/WHEEL
