Metadata-Version: 2.1
Name: pysseract
Version: 1.3.1
Summary: Python binding to Tesseract API
Home-page: https://github.com/xiahongze/pysseract
Author: Hongze Xia and Stephen Hogg
Author-email: hz.x@outlook.com
Maintainer: Hongze Xia
Maintainer-email: hz.x@outlook.com
License: MIT
Platform: UNKNOWN
Classifier: Development Status :: 5 - Production/Stable
Classifier: Framework :: Setuptools Plugin
Classifier: Framework :: Sphinx :: Theme
Classifier: Intended Audience :: Developers
Classifier: Intended Audience :: Science/Research
Classifier: License :: OSI Approved :: MIT License
Classifier: Operating System :: Unix
Classifier: Programming Language :: C++
Classifier: Programming Language :: Python :: 3 :: Only
Classifier: Topic :: Scientific/Engineering :: Image Recognition
Classifier: Topic :: Scientific/Engineering :: Information Analysis
Provides-Extra: build_sphinx
Provides-Extra: build_sphinx
Requires-Dist: m2r; extra == 'build_sphinx'
